whitepeaks/__init__.py
whitepeaks/analytics/__init__.py
whitepeaks/analytics/fft.py
whitepeaks/analytics/fitGaussian.py
whitepeaks/analytics/fitPolynomial.py
whitepeaks/analytics/functions.py
whitepeaks/analytics/stats.py
whitepeaks/interface/__init__.py
whitepeaks/interface/binner.py
whitepeaks/interface/io.py
whitepeaks/interface/postProcessing.py
whitepeaks/methods/__init__.py
whitepeaks/methods/frogalgo.py
whitepeaks/methods/gsalgo.py
whitepeaks/methods/sfg.py
whitepeaks/states/__init__.py
whitepeaks/states/measure.py
whitepeaks/states/photonStates.py
whitepeaks/states/pulses.py
whitepeaks/states/waveplates.py
whitepeaks/states/xstal.py
whitepeaks-0.0.1.dist-info/LICENSE.txt
whitepeaks-0.0.1.dist-info/METADATA
whitepeaks-0.0.1.dist-info/WHEEL
whitepeaks-0.0.1.dist-info/top_level.txt
whitepeaks-0.0.1.dist-info/RECORD
