Metadata-Version: 2.1
Name: whitepeaks
Version: 0.0.1
Summary: Ultrafast Quantum Optics Package containing phase retrieval algorithms using
Home-page: https://github.com/SachaSchwarz/whitepeaks
Author: Sacha Schwarz
Author-email: sacha.schwarz@gmail.com
License: UNKNOWN
Platform: UNKNOWN
Classifier: Programming Language :: Python :: 3
Classifier: License :: OSI Approved :: MIT License
Classifier: Operating System :: OS Independent
Requires-Python: >=3.6
